tcvpigpiv/__init__.py
tcvpigpiv/climatology.py
tcvpigpiv/era5_loader.py
tcvpigpiv/vpigpiv_module.py
tcvpigpiv-0.3.0.dist-info/licenses/LICENSE
tcvpigpiv-0.3.0.dist-info/METADATA
tcvpigpiv-0.3.0.dist-info/WHEEL
tcvpigpiv-0.3.0.dist-info/top_level.txt
tcvpigpiv-0.3.0.dist-info/RECORD
