Metadata-Version: 2.4
Name: tcvpigpiv
Version: 0.3.0
Summary: Calculate the tropical cyclone ventilated Potential Intensity (vPI) and the Genesis Potential Index using vPI (GPIv) from gridded datafiles. Supports both monthly mean and hourly ERA5 data. See Chavas Camargo Tippett (2025, J. Clim.) for details.
Home-page: https://github.com/drchavas/tcvpigpiv
Author: Dan Chavas, Jose Ocegueda Sanchez
Author-email: drchavas@gmail.com
License: MIT
Classifier: Programming Language :: Python :: 3
Classifier: Programming Language :: Python :: 3.8
Classifier: Programming Language :: Python :: 3.9
Classifier: Programming Language :: Python :: 3.10
Classifier: Programming Language :: Python :: 3.11
Classifier: Programming Language :: Python :: 3.12
Classifier: License :: OSI Approved :: MIT License
Classifier: Operating System :: OS Independent
Classifier: Intended Audience :: Science/Research
Classifier: Topic :: Scientific/Engineering :: Atmospheric Science
Requires-Python: >=3.8
License-File: LICENSE
Requires-Dist: numpy
Requires-Dist: xarray
Requires-Dist: netCDF4
Requires-Dist: tcpyPI
Requires-Dist: pandas
Provides-Extra: plot
Requires-Dist: matplotlib; extra == "plot"
Requires-Dist: cartopy; extra == "plot"
Provides-Extra: dev
Requires-Dist: pytest; extra == "dev"
Dynamic: author
Dynamic: author-email
Dynamic: classifier
Dynamic: description
Dynamic: description-content-type
Dynamic: home-page
Dynamic: license
Dynamic: license-file
Dynamic: provides-extra
Dynamic: requires-dist
Dynamic: requires-python
Dynamic: summary
